LICENSE
MANIFEST.in
README.rst
setup.py
django_financial_transactions.egg-info/PKG-INFO
django_financial_transactions.egg-info/SOURCES.txt
django_financial_transactions.egg-info/dependency_links.txt
django_financial_transactions.egg-info/requires.txt
django_financial_transactions.egg-info/top_level.txt
financial_transactions/__init__.py
financial_transactions/admin.py
financial_transactions/models.py
financial_transactions/utils.py
financial_transactions/forms/__init__.py
financial_transactions/forms/commerzbank.py
financial_transactions/management/__init__.py
financial_transactions/management/commands/__init__.py
financial_transactions/management/commands/import_transactions.py
financial_transactions/migrations/0001_initial.py
financial_transactions/migrations/__init__.py
financial_transactions/tests/__init__.py
financial_transactions/tests/test_models.py
financial_transactions/tests/test_utils.py
financial_transactions/tests/transaction_forms/__init__.py
financial_transactions/tests/transaction_forms/test_commerzbank.py