Metadata-Version: 1.1
Name: django-financial-transactions
Version: 0.2
Summary: A Django app to import and categorise financial transactions.
Home-page: http://github.com/absoludity/django-financial-transactions
Author: Michael Nelson
Author-email: absoludity@gmail.com
License: BSD License
Platform: UNKNOWN
Classifier: Environment :: Web Environment
Classifier: Framework :: Django
Classifier: Intended Audience :: Developers
Classifier: License :: OSI Approved :: BSD License
Classifier: Operating System :: OS Independent
Classifier: Programming Language :: Python
Classifier: Programming Language :: Python :: 2.6
Classifier: Programming Language :: Python :: 2.7
Classifier: Topic :: Internet :: WWW/HTTP
Classifier: Topic :: Internet :: WWW/HTTP :: Dynamic Content
